verilog_hardware/FSM_BASICS/lamp.v
module cyclic_lamp(clock , light);

input clock;
output reg [2:0] light;

 parameter s0 = 2'd0, s1 = 2'd1, s2 = 2'd2;
parameter  RED= 3'b100, GREEN= 3'b010, YELLOW= 3'b001;
reg[0:1] state;
always @(posedge clock)
case (state)
    s0: begin
      light <= GREEN; state <= s1;
    end
    s1: begin
      light <= YELLOW; state <= s2;
    end
    s2: begin
      light <= RED; state <= s0;
    end
    default: begin
      light <= RED;
      state <= s0;
    end
endcase
endmodule

verilog_hardware/FSM_BASICS/cyclic_lamp_test.v
`timescale 10ns/1ps
`include "lamp.v"

module cyclic_lamp_test;
reg clk;
wire [2:0] light;
cyclic_lamp lamp (.clock(clk),.light(light));
always #5 clk = ~clk;
initial 
begin
    clk = 1'b0;
    #100 $finish;
end
initial
 begin
    $dumpfile("cyclic_lamp_test.vcd");
    $dumpvars(0,cyclic_lamp_test);
    $monitor($time,"RGY:%b",light);
 end

endmodule

verilog_hardware/FSM_BASICS/cyclic_lamp_test.vcd
$date
	Wed Jul 02 18:18:51 2025
$end
$version
	Icarus Verilog
$end
$timescale
	1ps
$end
$scope module cyclic_lamp_test $end
$var wire 3 ! light [2:0] $end
$var reg 1 " clk $end
$scope module lamp $end
$var wire 1 " clock $end
$var parameter 3 # GREEN $end
$var parameter 3 $ RED $end
$var parameter 3 % YELLOW $end
$var parameter 2 & s0 $end
$var parameter 2 ' s1 $end
$var parameter 2 ( s2 $end
$var reg 3 ) light [2:0] $end
$var reg 2 * state [0:1] $end
$upscope $end
$upscope $end
$enddefinitions $end
$comment Show the parameter values. $end
$dumpall
b10 (
b1 '
b0 &
b1 %
b100 $
b10 #
$end
#0
$dumpvars
bx *
bx )
0"
bx !
$end
#50000
b0 *
b100 !
b100 )
1"
#100000
0"
#150000
b1 *
b10 !
b10 )
1"
#200000
0"
#250000
b10 *
b1 !
b1 )
1"
#300000
0"
#350000
b0 *
b100 !
b100 )
1"
#400000
0"
#450000
b1 *
b10 !
b10 )
1"
#500000
0"
#550000
b10 *
b1 !
b1 )
1"
#600000
0"
#650000
b0 *
b100 !
b100 )
1"
#700000
0"
#750000
b1 *
b10 !
b10 )
1"
#800000
0"
#850000
b10 *
b1 !
b1 )
1"
#900000
0"
#950000
b0 *
b100 !
b100 )
1"
