verilog_hardware/FSM_BASICS/parity_checker.v
module parity_gen(z,clk,x);
input clk,x;
output reg z;
parameter EVEN = 0,ODD = 1;
reg even_odd;
always @(posedge clk )
 case (even_odd)
    EVEN : even_odd <= x  ? ODD :EVEN;
    ODD  : even_odd <=  x ? EVEN:ODD;
    default: even_odd <= EVEN;
 endcase
 always @(even_odd)
case (even_odd)
     EVEN:  z = 0;
     ODD: z = 1;
   
endcase

endmodule

verilog_hardware/FSM_BASICS/parity_checker_test.v
`timescale 10ns/1ps
`include "parity_checker.v"

module parity_checker_test;

reg clk,in;
wire f;
parity_gen PAR (.z(f),.clk(clk),.x(in));
initial
 begin
    $dumpfile("parity_checker_test.vcd");
    $dumpvars(0,parity_checker_test);
    $monitor($time,"z:%b",f);
    clk = 1'b0;
end
always  #5 clk = ~clk;
initial 
begin
  #2   in =0; #10 in =1; #10 in =1; #10 in =1;
  #10  in =0; #10 in =1; #10 in =1; #10 in =0;
  #10  in =0; #10 in =1; #10 in =1; #10 in =0;
  $display("test completed!");
  #10 $finish;
end
    
endmodule

verilog_hardware/FSM_BASICS/parity_checker_test.vcd
$date
	Thu Jul 03 13:55:11 2025
$end
$version
	Icarus Verilog
$end
$timescale
	1ps
$end
$scope module parity_checker_test $end
$var wire 1 ! f $end
$var reg 1 " clk $end
$var reg 1 # in $end
$scope module PAR $end
$var wire 1 " clk $end
$var wire 1 # x $end
$var parameter 32 $ EVEN $end
$var parameter 32 % ODD $end
$var reg 1 & even_odd $end
$var reg 1 ! z $end
$upscope $end
$upscope $end
$enddefinitions $end
$comment Show the parameter values. $end
$dumpall
b1 %
b0 $
$end
#0
$dumpvars
x&
x#
0"
x!
$end
#20000
0#
#50000
0!
0&
1"
#100000
0"
#120000
1#
#150000
1!
1&
1"
#200000
0"
#250000
0!
0&
1"
#300000
0"
#350000
1!
1&
1"
#400000
0"
#420000
0#
#450000
1"
#500000
0"
#520000
1#
#550000
0!
0&
1"
#600000
0"
#650000
1!
1&
1"
#700000
0"
#720000
0#
#750000
1"
#800000
0"
#850000
1"
#900000
0"
#920000
1#
#950000
0!
0&
1"
#1000000
0"
#1050000
1!
1&
1"
#1100000
0"
#1120000
0#
