verilog_hardware/Project_ALU/alu_4bit.v
module alu_4bit(
    input  [3:0] A,
    input  [3:0] B,
    input  [3:0] ALU_Sel,
    output reg [3:0] ALU_Out,
    output reg CarryOut,
    output ZeroFlag
);

reg [4:0] temp_result;

assign ZeroFlag = (ALU_Out == 4'b0000);

always @(*) begin
    CarryOut = 0;
    case (ALU_Sel)
        4'b0000: begin // Addition
            temp_result = A + B;
            ALU_Out = temp_result[3:0];
            CarryOut = temp_result[4];
        end
        4'b0001: begin // Subtraction
            temp_result = A - B;
            ALU_Out = temp_result[3:0];
            CarryOut = temp_result[4]; // Borrow (if any)
        end
        4'b0010: begin // Bitwise AND
            ALU_Out = A & B;
            CarryOut = 0;
        end
        4'b0011: begin // Bitwise OR
            ALU_Out = A | B;
            CarryOut = 0;
        end
        4'b0100: begin // Bitwise XOR
            ALU_Out = A ^ B;
            CarryOut = 0;
        end
        4'b0101: begin // Logical Shift Left
            ALU_Out = A << 1;
            CarryOut = A[3]; // MSB shifted out
        end
        4'b0110: begin // Logical Shift Right
            ALU_Out = A >> 1;
            CarryOut = A[0]; // LSB shifted out
        end
        4'b0111: begin // Rotate Left
            ALU_Out = {A[2:0], A[3]};
            CarryOut = A[3];
        end
        4'b1000: begin // Rotate Right
            ALU_Out = {A[0], A[3:1]};
            CarryOut = A[0];
        end
        default: begin
            ALU_Out = 4'b0000;
            CarryOut = 0;
        end
    endcase
end

endmodule

verilog_hardware/Project_ALU/tb_alu_4bit.v
`timescale 1ns/1ps

module tb_alu_4bit;
    reg [3:0] A, B;
    reg [3:0] ALU_Sel;
    wire [3:0] ALU_Out;
    wire CarryOut;
    wire ZeroFlag;

    alu_4bit uut (
        .A(A),
        .B(B),
        .ALU_Sel(ALU_Sel),
        .ALU_Out(ALU_Out),
        .CarryOut(CarryOut),
        .ZeroFlag(ZeroFlag)
    );

    initial begin
        $dumpfile("alu_4bit.vcd");
        $dumpvars(0, tb_alu_4bit);

        // Test Addition
        A = 4'd7; B = 4'd8; ALU_Sel = 4'b0000; #10;
        $display("Add: %d + %d = %d, Carry = %b, ZeroFlag = %b", A, B, ALU_Out, CarryOut, ZeroFlag);

        // Test Subtraction
        A = 4'd9; B = 4'd3; ALU_Sel = 4'b0001; #10;
        $display("Sub: %d - %d = %d, Borrow = %b, ZeroFlag = %b", A, B, ALU_Out, CarryOut, ZeroFlag);

        // Test AND
        A = 4'b1010; B = 4'b1100; ALU_Sel = 4'b0010; #10;
        $display("AND: %b & %b = %b", A, B, ALU_Out);

        // Test OR
        A = 4'b1010; B = 4'b0101; ALU_Sel = 4'b0011; #10;
        $display("OR: %b | %b = %b", A, B, ALU_Out);

        // Test XOR
        A = 4'b1111; B = 4'b1010; ALU_Sel = 4'b0100; #10;
        $display("XOR: %b ^ %b = %b", A, B, ALU_Out);

        // Test Shift Left
        A = 4'b1001; ALU_Sel = 4'b0101; #10;
        $display("Shift Left: %b << 1 = %b, Carry = %b", A, ALU_Out, CarryOut);

        // Test Shift Right
        A = 4'b1001; ALU_Sel = 4'b0110; #10;
        $display("Shift Right: %b >> 1 = %b, Carry = %b", A, ALU_Out, CarryOut);

        // Test Rotate Left
        A = 4'b1001; ALU_Sel = 4'b0111; #10;
        $display("Rotate Left: %b rol 1 = %b, Carry = %b", A, ALU_Out, CarryOut);

        // Test Rotate Right
        A = 4'b1001; ALU_Sel = 4'b1000; #10;
        $display("Rotate Right: %b ror 1 = %b, Carry = %b", A, ALU_Out, CarryOut);

        $finish;
    end
endmodule

verilog_hardware/Project_ALU/alu_4bit.vcd
$date
	Fri Aug 08 09:42:42 2025
$end
$version
	Icarus Verilog
$end
$timescale
	1ps
$end
$scope module tb_alu_4bit $end
$var wire 1 ! ZeroFlag $end
$var wire 1 " CarryOut $end
$var wire 4 # ALU_Out [3:0] $end
$var reg 4 $ A [3:0] $end
$var reg 4 % ALU_Sel [3:0] $end
$var reg 4 & B [3:0] $end
$scope module uut $end
$var wire 4 ' A [3:0] $end
$var wire 4 ( ALU_Sel [3:0] $end
$var wire 4 ) B [3:0] $end
$var wire 1 ! ZeroFlag $end
$var reg 4 * ALU_Out [3:0] $end
$var reg 1 " CarryOut $end
$var reg 5 + temp_result [4:0] $end
$upscope $end
$upscope $end
$enddefinitions $end
$comment Show the parameter values. $end
$dumpall
$end
#0
$dumpvars
b1111 +
b1111 *
b1000 )
b0 (
b111 '
b1000 &
b0 %
b111 $
b1111 #
0"
0!
$end
#10000
b110 #
b110 *
b110 +
b1 %
b1 (
b11 &
b11 )
b1001 $
b1001 '
#20000
b1000 #
b1000 *
b10 %
b10 (
b1100 &
b1100 )
b1010 $
b1010 '
#30000
b1111 #
b1111 *
b11 %
b11 (
b101 &
b101 )
#40000
b101 #
b101 *
b100 %
b100 (
b1010 &
b1010 )
b1111 $
b1111 '
#50000
1"
b10 #
b10 *
b101 %
b101 (
b1001 $
b1001 '
#60000
b100 #
b100 *
1"
b110 %
b110 (
#70000
b11 #
b11 *
1"
b111 %
b111 (
#80000
b1100 #
b1100 *
1"
b1000 %
b1000 (
