verilog_hardware/simple_combinational_logic_design/greater_then.v
module greater_then(A,B,F);

input[1:0] A,B;
output F;


//  assign F = A > B;
//  assign F = A[1] & ~B[1] | A[0] & ~B[1] & ~B[0] | A[1] & A[0] & ~B[0] & ~B[1];


assign F = (A[1] & ~B[1]) |                     // MSB comparison
           (~A[1] & ~B[1] & A[0] & ~B[0]) |     // MSBs equal to 0, check LSB
           (A[1] & B[1] & A[0] & ~B[0]); 

endmodule

verilog_hardware/simple_combinational_logic_design/greater_then_tb.v
 `timescale 1 ns/1 ns
 `include "greater_then.v"


module greater_then_tb;

reg[1:0] A,B;
wire F;
greater_then uut(A,B,F);

initial begin
    
   $dumpfile("greater_then_tb.vcd");
   $dumpvars(0,greater_then_tb);

   {A,B} = 4'd0; #20;
   {A,B} = 4'd1; #20;
   {A,B} = 4'd2; #20;
   {A,B} = 4'd3; #20;
   {A,B} = 4'd4; #20;
   {A,B} = 4'd5; #20;
   {A,B} = 4'd6; #20;
   {A,B} = 4'd7; #20;
   {A,B} = 4'd8; #20;
   {A,B} = 4'd9; #20;
   {A,B} = 4'd10; #20;
   {A,B} = 4'd11; #20;
   {A,B} = 4'd12; #20;
   {A,B} = 4'd13; #20;
   {A,B} = 4'd14; #20;
   {A,B} = 4'd15; #20;

  $display("test complete");

end


endmodule

verilog_hardware/simple_combinational_logic_design/greater_then_tb.vcd
$date
	Sun Jun 08 21:55:39 2025
$end
$version
	Icarus Verilog
$end
$timescale
	1ns
$end
$scope module greater_then_tb $end
$var wire 1 ! F $end
$var reg 2 " A [1:0] $end
$var reg 2 # B [1:0] $end
$scope module uut $end
$var wire 2 $ A [1:0] $end
$var wire 2 % B [1:0] $end
$var wire 1 ! F $end
$upscope $end
$upscope $end
$enddefinitions $end
$comment Show the parameter values. $end
$dumpall
$end
#0
$dumpvars
b0 %
b0 $
b0 #
b0 "
0!
$end
#20
b1 #
b1 %
#40
b10 #
b10 %
#60
b11 #
b11 %
#80
1!
b1 "
b1 $
b0 #
b0 %
#100
0!
b1 #
b1 %
#120
0!
b10 #
b10 %
#140
b11 #
b11 %
#160
1!
b10 "
b10 $
b0 #
b0 %
#180
b1 #
b1 %
#200
0!
b10 #
b10 %
#220
b11 #
b11 %
#240
1!
b11 "
b11 $
b0 #
b0 %
#260
b1 #
b1 %
#280
b10 #
b10 %
#300
0!
b11 #
b11 %
